parse_1c_build-5.15.9.dist-info/METADATA
parse_1c_build-5.15.9.dist-info/WHEEL
parse_1c_build-5.15.9.dist-info/entry_points.txt
parse_1c_build/__about__.py
parse_1c_build/__init__.py
parse_1c_build/__main__.py
parse_1c_build/base.py
parse_1c_build/build.py
parse_1c_build/cli.py
parse_1c_build/core.py
parse_1c_build/parse.py
tests/__init__.py
tests/data/settings.yaml
tests/data/test.epf
tests/data/test_epf_src/maps.txt
tests/data/test_epf_src/renames.txt
tests/data/test_epf_src/und/899371e7-3efb-46bf-940e-a47cd76913cd
tests/data/test_epf_src/und/copyinfo
tests/data/test_epf_src/und/root
tests/data/test_epf_src/und/version
tests/data/test_epf_src/und/versions
tests/test_base.py
tests/test_build.py
tests/test_parse.py
parse_1c_build-5.15.9.dist-info/RECORD
