Metadata-Version: 2.1
Name: parse-1c-build
Version: 5.15.9
Summary: Parse and build utilities for 1C:Enterprise
Keywords: 1c,parse,build,v8reader,v8unpack,gcomp
Author-Email: Cujoko <cujoko@gmail.com>
License: MIT
Classifier: Development Status :: 5 - Production/Stable
Classifier: Intended Audience :: Developers
Classifier: License :: OSI Approved :: MIT License
Classifier: Natural Language :: Russian
Classifier: Programming Language :: Python :: 3.14
Classifier: Programming Language :: Python :: 3.13
Classifier: Programming Language :: Python :: 3.12
Classifier: Programming Language :: Python :: 3.11
Classifier: Programming Language :: Python :: 3.10
Classifier: Topic :: Software Development
Classifier: Topic :: Utilities
Project-URL: repository, https://github.com/Cujoko-Dev/parse-1c-build
Requires-Python: >=3.10
Requires-Dist: cjk-commons<4.0.0,>=3.6.3
Requires-Dist: commons-1c<4.0.0,>=3.6.3
Requires-Dist: loguru>=0.6.0
